pollination_streamlit/__init__.py
pollination_streamlit/authentication.py
pollination_streamlit/dataframe.py
pollination_streamlit/interactors.py
pollination_streamlit/selectors.py
pollination_streamlit/api/__init__.py
pollination_streamlit/api/_base.py
pollination_streamlit/api/client.py
pollination_streamlit/api/jobs.py
pollination_streamlit/api/recipes.py
pollination_streamlit/api/runs.py
pollination_streamlit/api/user.py
pollination_streamlit-0.8.3.dist-info/LICENSE
pollination_streamlit-0.8.3.dist-info/METADATA
pollination_streamlit-0.8.3.dist-info/WHEEL
pollination_streamlit-0.8.3.dist-info/top_level.txt
pollination_streamlit-0.8.3.dist-info/RECORD
