Metadata-Version: 2.1
Name: pollination-streamlit
Version: 0.8.3
Summary: A Pollination extension to facilitate working with Pollination in Streamlit apps.
Home-page: https://github.com/pollination/pollination-streamlit
Author: Pollination
Author-email: info@pollination.cloud
License: Apache-2.0 License
Platform: UNKNOWN
Classifier: Programming Language :: Python :: 3.10
Classifier: Programming Language :: Python :: Implementation :: CPython
Classifier: License :: OSI Approved :: Apache Software License
Classifier: Operating System :: OS Independent
License-File: LICENSE
Requires-Dist: streamlit (>=1.20.0)
Requires-Dist: extra-streamlit-components (>=0.1.53)
Requires-Dist: pollination-io (>=1.0.3)
Requires-Dist: requests
Requires-Dist: queenbee
